<?xml version="1.0" encoding="windows-1251"?>
<config><_other type="a"><alias_exists type="s" descr="Псевдоним существует" value="Такой уже псевдоним существует!"/><module_error type="s" descr="Ошибка в модуле" value="Ошибка в программном модуле !"/><module_absent type="s" descr="Модуль не задан" value="Модуль не задан !"/></_other><alias type="a" descr="Псевдоним"><_ruls type="s" descr="" value="nn;len|20;match|[a-z\d_]+"/><nn type="s" descr="Пустое поле" value="Псевдоним не может быть пустым"/><len type="s" descr="Длина строки" value="Псевдоним не может превышать 20 символов"/><match type="s" descr="RegExp" value="В псевдониме содердатся недопустимые символы"/></alias><name type="a" descr="Название"><_ruls type="s" descr="" value="nn;len|40"/><nn type="s" descr="Пустое поле" value="Название раздела не должно быть пустым !"/><len type="s" descr="Длина строки" value="Название раздела не может превышать 40 символов !"/></name><fullname type="a" descr="Полное название"><_ruls type="s" descr="" value="len|100"/><len type="s" descr="Длина строки" value="Полное название раздела не может превышать 100 символов !"/></fullname></config>
